mirasol_pytorch/__init__.py
mirasol_pytorch/distributed.py
mirasol_pytorch/mirasol_pytorch.py
mirasol_pytorch-0.0.16.dist-info/LICENSE
mirasol_pytorch-0.0.16.dist-info/METADATA
mirasol_pytorch-0.0.16.dist-info/WHEEL
mirasol_pytorch-0.0.16.dist-info/top_level.txt
mirasol_pytorch-0.0.16.dist-info/RECORD
