Metadata-Version: 2.1
Name: mirasol-pytorch
Version: 0.0.16
Summary: Mirasol - Pytorch
Home-page: https://github.com/lucidrains/mirasol-pytorch
Author: Phil Wang
Author-email: lucidrains@gmail.com
License: MIT
Keywords: artificial intelligence,deep learning,multimodality
Classifier: Development Status :: 4 - Beta
Classifier: Intended Audience :: Developers
Classifier: Topic :: Scientific/Engineering :: Artificial Intelligence
Classifier: License :: OSI Approved :: MIT License
Classifier: Programming Language :: Python :: 3.6
License-File: LICENSE
Requires-Dist: beartype
Requires-Dist: einops >=0.7.0
Requires-Dist: x-transformers >=1.25.10
Requires-Dist: torch >=2.0
